setup.py
funniest121/__init__.py
funniest121.egg-info/PKG-INFO
funniest121.egg-info/SOURCES.txt
funniest121.egg-info/dependency_links.txt
funniest121.egg-info/not-zip-safe
funniest121.egg-info/top_level.txt