Metadata-Version: 1.0
Name: funniest121
Version: 0.1
Summary: The funniest joke in the world
Home-page: http://github.com/storborg/funniest
Author: Ashutosh
Author-email: ashu.beginner@gmail.com
License: MIT
Platform: UNKNOWN
